[
	{
		"theme": "彩釉斗艳",
		"titles": [
			{
				"title": "五彩瓷的艺术特色有哪些？粉彩有哪些优势？它们的区别有哪些？",
				"url": ""
			},
			{
				"title": "你觉得珐琅彩有哪些创新之处？",
				"url": ""
			},
			{
				"title": "你认为推动釉上彩瓷发展的主要因素是什么？当代科技这么发达能否制造出比以前更好的彩瓷瓷器？",
				"url": ""
			}
		]
	},
	{
		"theme": "五霸七雄",
		"titles": [
			{
				"title": "你能找出春秋战国时期与国家发展相关的典故吗？",
				"url": ""
			},
			{
				"title": "六国灭亡的原因是什么？这对现代人为人处世有什么启示？",
				"url": ""
			},
			{
				"title": "梳理钱币发展的历史。",
				"url": ""
			}
		]
	},
	{
		"theme": "鼎盛中华",
		"titles": [
			{
				"title": "列举带、“鼎”字的成语，简单解释包含的意思，总结鼎的实际使用功能是什么？鼎象征什么？",
				"url": ""
			},
			{
				"title": "不同时期的鼎打着时代的烙印，楚鼎很有名，你结合网上学习阐释它反映什么样的楚文化？",
				"url": ""
			}
		]
	},
	{
		"theme": "青花幽蓝",
		"titles": [
			{
				"title": "不同年代、青花瓷器的器型、颜色、纹饰都是不一样的，你能对这些问题加以展开论述吗？",
				"url": ""
			},
			{
				"title": "青花瓷的“美”表现在哪些地方，从多角度说明。",
				"url": ""
			},
			{
				"title": "请你设计一款表现现代特征的青花瓷器，说说你设计的依据。",
				"url": ""
			}
		]
	},
	{
		"theme": "承坐之间",
		"titles": [
			{
				"title": "你认为中国古代家具的设计体现了古人的哪些智慧和情怀？",
				"url": ""
			},
			{
				"title": "请你尽可能多的列举带“桌”字，带“案”字的成语或词语，体味在古代人民的生活中蕴含的精神文化寄托。",
				"url": ""
			},
			{
				"title": "中国古代家具和现代家具在审美上有何不同，请以某一个朝代或一个时代来说明。",
				"url": ""
			}
		]
	},
	{
		"theme": "国防建设",
		"titles": [
			{
				"title": "国家领导人多次提出裁军，1985年、2015年提出裁军的历史背景和意义有哪些？",
				"url": ""
			},
			{
				"title": "从我国的国家地位的变化，看国防建设发生了怎样的变化？请用数字、事实说话。",
				"url": ""
			},
			{
				"title": "给大家介绍一种你喜欢的兵器知识。",
				"url": ""
			}
		]
	},
	{
		"theme": "生存的抗争",
		"titles": [
			{
				"title": "人类发明使用工具是一个过程，你研究一下，分几个阶段？",
				"url": ""
			},
			{
				"title": "华夏民族为了生存做了哪些抗争，你能举实例说明那些抗争的重要影响。",
				"url": ""
			},
			{
				"title": "今天，我们面临哪些威胁？作为中学生在这些威胁面前应该怎么做？",
				"url": ""
			}
		]
	},
	{
		"theme": "观形识义",
		"titles": [
			{
				"title": "甲骨文在造字方式上有哪些特点？对今天汉字的影响是什么？",
				"url": ""
			},
			{
				"title": "如何欣赏甲骨文的美？",
				"url": ""
			},
			{
				"title": "甲骨文的书体风格与现代很多艺术相融通，你能找出与哪些艺术、生活相融通，并谈谈你的感受。",
				"url": ""
			}
		]
	},
	{
		"theme": "神龙出世六千年",
		"titles": [
			{
				"title": "中国有“龙”图腾崇拜的习惯，请你结合博物馆学习，阐释“龙”从形象、文化内涵等方面的发展历程。",
				"url": ""
			},
			{
				"title": "龙在中国有6000年历史了，请你举例说明在不同的历史时期，“龙”对中国人的生活和社会发展有哪些影响？",
				"url": ""
			},
			{
				"title": "请你根据自己的兴趣爱好，能都设计一个“龙”系列图样，可以是学习用品，或者生活用品等。体现你的审美特点。",
				"url": ""
			}
		]
	},
	{
		"theme": "三彩世界",
		"titles": [
			{
				"title": "我所了解的唐三彩",
				"url": ""
			},
			{
				"title": "丝绸之路对唐朝人的生活有哪些影响？",
				"url": ""
			},
			{
				"title": "丝绸之路对东西方各个方面的交流和影响有哪些贡献？",
				"url": ""
			},
			{
				"title": "现在的“一带一路”对中国的发展非常重要，这里的“路”就是丝绸之路，请你结合自己熟悉的生活谈谈现在的丝绸之路对我们的影响。",
				"url": ""
			}
		]
	},
	{
		"theme": "成语服饰",
		"titles": [
			{
				"title": "根据博物馆学习，你能叙述各个朝代穿着的特点吗？",
				"url": ""
			},
			{
				"title": "请以你喜欢的某一个朝代为例，说说这个朝代的穿着反应了当时怎样的文化？",
				"url": ""
			},
			{
				"title": "在现代服饰中，哪些元素继承了中国古代服饰的特点。",
				"url": ""
			},
			{
				"title": "如果让你给2022年冬奥会运动员设计一款服装，你认为什么样的元素是必须有的？为什么？",
				"url": ""
			}
		]
	}
]